kuna/__init__.py
kuna/cli.py
kuna/kuna.py
kuna-0.4.0.dist-info/AUTHORS.rst
kuna-0.4.0.dist-info/LICENSE
kuna-0.4.0.dist-info/METADATA
kuna-0.4.0.dist-info/WHEEL
kuna-0.4.0.dist-info/entry_points.txt
kuna-0.4.0.dist-info/top_level.txt
kuna-0.4.0.dist-info/RECORD
