Metadata-Version: 2.1
Name: kuna
Version: 0.4.0
Summary: Interact with Kuna exchange API
Home-page: https://github.com/DmytroLitvinov/kuna
Author: Dmytro Litvinov
Author-email: me@dmytrolitvinov.com
License: MIT license
Keywords: kuna
Platform: UNKNOWN
Classifier: Development Status :: 4 - Beta
Classifier: Intended Audience :: Developers
Classifier: License :: OSI Approved :: MIT License
Classifier: Natural Language :: English
Classifier: Programming Language :: Python
Classifier: Programming Language :: Python :: 3
Classifier: Programming Language :: Python :: 3.6
Classifier: Programming Language :: Python :: 3.7
Classifier: Programming Language :: Python :: 3.8
Classifier: Programming Language :: Python :: 3.9
Requires-Dist: Click (>=6.0)
